{
   "stats" : {
      "Out of Conference" : {
         "attempted3Pt" : 2,
         "assists" : 6,
         "madeFt" : 16,
         "gameCount" : 4,
         "gameNumber" : 0,
         "made2Pt" : 27,
         "fouls" : 14,
         "defRebounds" : 25,
         "percent2Pt" : "62.8%",
         "steals" : 4,
         "attemptedFt" : 23,
         "opponent" : 0,
         "pointsTotal" : 73,
         "attempted2Pt" : 43,
         "made3Pt" : 1,
         "blocks" : 12,
         "percentFt" : "69.6%",
         "reboundsTotal" : 35,
         "offRebounds" : 10,
         "turnovers" : 11,
         "percent3Pt" : "50.0%",
         "percentTotal" : "62.2%",
         "averages" : {
            "aveOffRebounds" : 2.5,
            "aveRebounds" : 8.8,
            "aveTurnovers" : 2.8,
            "games" : 4,
            "avePoints" : 18.2,
            "aveAssists" : 1.5,
            "aveSteals" : 1,
            "aveDefRebounds" : 6.2,
            "aveFouls" : 3.5,
            "aveBlocks" : 3
         }
      },
      "State" : {
         "pointsTotal" : 56,
         "attempted2Pt" : 33,
         "made3Pt" : 1,
         "blocks" : 4,
         "percent2Pt" : "54.5%",
         "steals" : 2,
         "attemptedFt" : 23,
         "opponent" : 0,
         "percentTotal" : "50.0%",
         "averages" : {
            "aveOffRebounds" : 2.3,
            "aveRebounds" : 7,
            "games" : 3,
            "avePoints" : 18.7,
            "aveTurnovers" : 3,
            "aveSteals" : 0.7,
            "aveAssists" : 0.3,
            "aveBlocks" : 1.3,
            "aveDefRebounds" : 4.7,
            "aveFouls" : 3.7
         },
         "percentFt" : "73.9%",
         "offRebounds" : 7,
         "reboundsTotal" : 21,
         "percent3Pt" : "20.0%",
         "turnovers" : 9,
         "assists" : 1,
         "attempted3Pt" : 5,
         "gameNumber" : 0,
         "made2Pt" : 18,
         "fouls" : 11,
         "defRebounds" : 14,
         "madeFt" : 17,
         "gameCount" : 3
      },
      "Conference" : {
         "averages" : {
            "aveBlocks" : 2.4,
            "aveFouls" : 3.6,
            "aveDefRebounds" : 5.6,
            "aveSteals" : 1.4,
            "aveAssists" : 1.5,
            "avePoints" : 15.8,
            "games" : 17,
            "aveTurnovers" : 3,
            "aveRebounds" : 7.6,
            "aveOffRebounds" : 2
         },
         "percentTotal" : "49.3%",
         "turnovers" : 51,
         "percent3Pt" : "25.0%",
         "reboundsTotal" : 130,
         "offRebounds" : 34,
         "percentFt" : "63.7%",
         "blocks" : 40,
         "made3Pt" : 3,
         "attempted2Pt" : 191,
         "pointsTotal" : 268,
         "opponent" : 0,
         "attemptedFt" : 102,
         "steals" : 23,
         "percent2Pt" : "50.8%",
         "defRebounds" : 96,
         "fouls" : 61,
         "made2Pt" : 97,
         "gameNumber" : 0,
         "gameCount" : 17,
         "madeFt" : 65,
         "assists" : 26,
         "attempted3Pt" : 12
      },
      "Districts" : {
         "attempted3Pt" : 0,
         "assists" : 2,
         "madeFt" : 9,
         "gameCount" : 2,
         "made2Pt" : 13,
         "gameNumber" : 0,
         "defRebounds" : 12,
         "fouls" : 3,
         "attemptedFt" : 14,
         "steals" : 0,
         "percent2Pt" : "50.0%",
         "opponent" : 0,
         "pointsTotal" : 35,
         "blocks" : 7,
         "made3Pt" : 0,
         "attempted2Pt" : 26,
         "turnovers" : 5,
         "percent3Pt" : "0.0%",
         "offRebounds" : 1,
         "reboundsTotal" : 13,
         "percentFt" : "64.3%",
         "averages" : {
            "aveAssists" : 1,
            "aveSteals" : 0,
            "aveDefRebounds" : 6,
            "aveFouls" : 1.5,
            "aveBlocks" : 3.5,
            "aveOffRebounds" : 0.5,
            "aveRebounds" : 6.5,
            "aveTurnovers" : 2.5,
            "games" : 2,
            "avePoints" : 17.5
         },
         "percentTotal" : "50.0%"
      },
      "Season" : {
         "averages" : {
            "aveBlocks" : 2.2,
            "aveFouls" : 3.4,
            "aveDefRebounds" : 5.6,
            "aveSteals" : 1,
            "aveAssists" : 1.4,
            "avePoints" : 16.8,
            "games" : 30,
            "aveTurnovers" : 3,
            "aveRebounds" : 7.6,
            "aveOffRebounds" : 2
         },
         "percentTotal" : "52.8%",
         "turnovers" : 89,
         "percent3Pt" : "25.0%",
         "offRebounds" : 60,
         "reboundsTotal" : 229,
         "percentFt" : "65.6%",
         "blocks" : 67,
         "made3Pt" : 5,
         "attempted2Pt" : 342,
         "pointsTotal" : 505,
         "opponent" : 0,
         "attemptedFt" : 180,
         "steals" : 31,
         "percent2Pt" : "54.4%",
         "defRebounds" : 169,
         "fouls" : 102,
         "made2Pt" : 186,
         "gameNumber" : 0,
         "gameCount" : 30,
         "madeFt" : 118,
         "assists" : 41,
         "attempted3Pt" : 20
      },
      "Regionals" : {
         "opponent" : 0,
         "attemptedFt" : 18,
         "percent2Pt" : "63.3%",
         "steals" : 2,
         "blocks" : 4,
         "attempted2Pt" : 49,
         "made3Pt" : 0,
         "pointsTotal" : 73,
         "offRebounds" : 8,
         "reboundsTotal" : 30,
         "turnovers" : 13,
         "percent3Pt" : "0.0%",
         "percentFt" : "61.1%",
         "percentTotal" : "62.0%",
         "averages" : {
            "games" : 4,
            "avePoints" : 18.2,
            "aveTurnovers" : 3.2,
            "aveOffRebounds" : 2,
            "aveRebounds" : 7.5,
            "aveBlocks" : 1,
            "aveDefRebounds" : 5.5,
            "aveFouls" : 3.2,
            "aveSteals" : 0.5,
            "aveAssists" : 1.5
         },
         "attempted3Pt" : 1,
         "assists" : 6,
         "gameCount" : 4,
         "madeFt" : 11,
         "defRebounds" : 22,
         "fouls" : 13,
         "made2Pt" : 31,
         "gameNumber" : 0
      }
   },
   "name" : "Schulz"
}
