{
   "name" : "Siefken",
   "stats" : {
      "Conference" : {
         "percent2Pt" : "33.3%",
         "attempted2Pt" : 3,
         "gameNumber" : 0,
         "turnovers" : 11,
         "offRebounds" : 2,
         "percentFt" : "60.0%",
         "fouls" : 3,
         "opponent" : 0,
         "madeFt" : 9,
         "defRebounds" : 5,
         "made3Pt" : 0,
         "steals" : 2,
         "percentTotal" : "33.3%",
         "gameCount" : 17,
         "pointsTotal" : 11,
         "averages" : {
            "games" : 17,
            "avePoints" : 0.6,
            "aveOffRebounds" : 0.1,
            "aveTurnovers" : 0.6,
            "aveAssists" : 0.4,
            "aveDefRebounds" : 0.3,
            "aveRebounds" : 0.4,
            "aveSteals" : 0.1,
            "aveBlocks" : 0.1,
            "aveFouls" : 0.2
         },
         "reboundsTotal" : 7,
         "attemptedFt" : 15,
         "blocks" : 1,
         "percent3Pt" : "0.0%",
         "made2Pt" : 1,
         "attempted3Pt" : 0,
         "assists" : 7
      },
      "Out of Conference" : {
         "turnovers" : 2,
         "percentFt" : "0.0%",
         "offRebounds" : 1,
         "attempted2Pt" : 1,
         "percent2Pt" : "100.0%",
         "gameNumber" : 0,
         "madeFt" : 0,
         "defRebounds" : 3,
         "opponent" : 0,
         "fouls" : 1,
         "gameCount" : 4,
         "percentTotal" : "16.7%",
         "steals" : 2,
         "made3Pt" : 0,
         "assists" : 2,
         "attempted3Pt" : 5,
         "percent3Pt" : "0.0%",
         "made2Pt" : 1,
         "averages" : {
            "aveRebounds" : 1.2,
            "aveSteals" : 0.5,
            "aveBlocks" : 0,
            "aveFouls" : 0.2,
            "games" : 4,
            "avePoints" : 0.5,
            "aveOffRebounds" : 0.2,
            "aveTurnovers" : 0.5,
            "aveAssists" : 0.5,
            "aveDefRebounds" : 0.8
         },
         "attemptedFt" : 0,
         "blocks" : 0,
         "reboundsTotal" : 5,
         "pointsTotal" : 2
      },
      "Regionals" : {
         "averages" : {
            "aveTurnovers" : 0.5,
            "aveAssists" : 0,
            "aveDefRebounds" : 0.2,
            "games" : 4,
            "avePoints" : 0,
            "aveOffRebounds" : 0.2,
            "aveFouls" : 0,
            "aveRebounds" : 0.5,
            "aveSteals" : 0,
            "aveBlocks" : 0
         },
         "reboundsTotal" : 2,
         "attemptedFt" : 0,
         "blocks" : 0,
         "pointsTotal" : 0,
         "attempted3Pt" : 0,
         "assists" : 0,
         "percent3Pt" : "0.0%",
         "made2Pt" : 0,
         "steals" : 0,
         "made3Pt" : 0,
         "gameCount" : 4,
         "percentTotal" : "0.0%",
         "opponent" : 0,
         "fouls" : 0,
         "defRebounds" : 1,
         "madeFt" : 0,
         "turnovers" : 2,
         "offRebounds" : 1,
         "percentFt" : "0.0%",
         "percent2Pt" : "0.0%",
         "attempted2Pt" : 0,
         "gameNumber" : 0
      },
      "State" : {
         "gameNumber" : 0,
         "percent2Pt" : "0.0%",
         "attempted2Pt" : 0,
         "offRebounds" : 0,
         "percentFt" : "0.0%",
         "turnovers" : 0,
         "fouls" : 0,
         "opponent" : 0,
         "madeFt" : 0,
         "defRebounds" : 0,
         "made3Pt" : 0,
         "steals" : 0,
         "percentTotal" : "0.0%",
         "gameCount" : 3,
         "pointsTotal" : 0,
         "reboundsTotal" : 0,
         "blocks" : 0,
         "attemptedFt" : 0,
         "averages" : {
            "aveFouls" : 0,
            "aveSteals" : 0,
            "aveRebounds" : 0,
            "aveBlocks" : 0,
            "aveTurnovers" : 0,
            "aveDefRebounds" : 0,
            "aveAssists" : 0,
            "avePoints" : 0,
            "games" : 3,
            "aveOffRebounds" : 0
         },
         "made2Pt" : 0,
         "percent3Pt" : "0.0%",
         "attempted3Pt" : 1,
         "assists" : 0
      },
      "Districts" : {
         "opponent" : 0,
         "fouls" : 0,
         "defRebounds" : 0,
         "madeFt" : 0,
         "offRebounds" : 0,
         "percentFt" : "0.0%",
         "turnovers" : 0,
         "gameNumber" : 0,
         "percent2Pt" : "0.0%",
         "attempted2Pt" : 0,
         "reboundsTotal" : 0,
         "attemptedFt" : 0,
         "blocks" : 0,
         "averages" : {
            "aveBlocks" : 0,
            "aveRebounds" : 0,
            "aveSteals" : 0,
            "aveFouls" : 0,
            "aveOffRebounds" : 0,
            "games" : 2,
            "avePoints" : 0,
            "aveAssists" : 0,
            "aveDefRebounds" : 0,
            "aveTurnovers" : 0
         },
         "pointsTotal" : 0,
         "attempted3Pt" : 0,
         "assists" : 0,
         "made2Pt" : 0,
         "percent3Pt" : "0.0%",
         "steals" : 0,
         "made3Pt" : 0,
         "gameCount" : 2,
         "percentTotal" : "0.0%"
      },
      "Season" : {
         "pointsTotal" : 13,
         "blocks" : 1,
         "attemptedFt" : 15,
         "reboundsTotal" : 14,
         "averages" : {
            "aveTurnovers" : 0.5,
            "aveDefRebounds" : 0.3,
            "aveAssists" : 0.3,
            "games" : 30,
            "avePoints" : 0.4,
            "aveOffRebounds" : 0.1,
            "aveFouls" : 0.1,
            "aveSteals" : 0.1,
            "aveRebounds" : 0.5,
            "aveBlocks" : 0
         },
         "made2Pt" : 2,
         "percent3Pt" : "0.0%",
         "assists" : 9,
         "attempted3Pt" : 6,
         "made3Pt" : 0,
         "steals" : 4,
         "percentTotal" : "20.0%",
         "gameCount" : 30,
         "fouls" : 4,
         "opponent" : 0,
         "madeFt" : 9,
         "defRebounds" : 9,
         "gameNumber" : 0,
         "attempted2Pt" : 4,
         "percent2Pt" : "50.0%",
         "percentFt" : "60.0%",
         "offRebounds" : 4,
         "turnovers" : 15
      }
   }
}
