{
   "stats" : [
      {
         "opponent" : "Kennewick Lions",
         "attemptedFt" : "0",
         "percent2Pt" : "0.00%",
         "steals" : "0",
         "blocks" : "0",
         "attempted2Pt" : "0",
         "made3Pt" : "0",
         "pointsTotal" : null,
         "offRebounds" : "0",
         "reboundsTotal" : null,
         "percent3Pt" : "0.00%",
         "turnovers" : "0",
         "percentFt" : "0.00%",
         "gameType" : "Districts",
         "percentTotal" : "0.00%",
         "attempted3Pt" : "0",
         "assists" : "0",
         "name" : "Mitchell",
         "madeFt" : "0",
         "defRebounds" : "0",
         "fouls" : "0",
         "made2Pt" : "0",
         "gameNumber" : 22
      },
      {
         "name" : "Mitchell",
         "assists" : "0",
         "attempted3Pt" : "0",
         "gameNumber" : 23,
         "made2Pt" : "0",
         "fouls" : "0",
         "defRebounds" : "0",
         "madeFt" : "0",
         "pointsTotal" : null,
         "made3Pt" : "0",
         "attempted2Pt" : "0",
         "blocks" : "0",
         "steals" : "0",
         "percent2Pt" : "0.00%",
         "attemptedFt" : "0",
         "opponent" : "Kamiakin Braves",
         "percentTotal" : "0.00%",
         "gameType" : "Districts",
         "percentFt" : "0.00%",
         "turnovers" : "0",
         "percent3Pt" : "0.00%",
         "offRebounds" : "0",
         "reboundsTotal" : null
      },
      {
         "gameNumber" : 24,
         "made2Pt" : "0",
         "fouls" : "0",
         "defRebounds" : "0",
         "madeFt" : "0",
         "name" : "Mitchell",
         "assists" : "0",
         "attempted3Pt" : "0",
         "percentTotal" : "0.00%",
         "gameType" : "Regionals",
         "percentFt" : "0.00%",
         "percent3Pt" : "0.00%",
         "turnovers" : "0",
         "offRebounds" : "0",
         "reboundsTotal" : null,
         "pointsTotal" : null,
         "made3Pt" : "0",
         "attempted2Pt" : "0",
         "blocks" : "0",
         "steals" : "0",
         "percent2Pt" : "0.00%",
         "attemptedFt" : "0",
         "opponent" : "Rogers Pirates"
      },
      {
         "fouls" : "0",
         "defRebounds" : "0",
         "gameNumber" : 25,
         "made2Pt" : "0",
         "madeFt" : "0",
         "name" : "Mitchell",
         "assists" : "0",
         "attempted3Pt" : "0",
         "gameType" : "Regionals",
         "percentTotal" : "0.00%",
         "percentFt" : "0.00%",
         "percent3Pt" : "0.00%",
         "turnovers" : "0",
         "offRebounds" : "0",
         "reboundsTotal" : null,
         "made3Pt" : "0",
         "attempted2Pt" : "0",
         "blocks" : "0",
         "pointsTotal" : null,
         "opponent" : "Mead Panthers",
         "steals" : "0",
         "percent2Pt" : "0.00%",
         "attemptedFt" : "0"
      },
      {
         "percentTotal" : "0.00%",
         "gameType" : "Regionals",
         "percentFt" : "0.00%",
         "offRebounds" : "0",
         "reboundsTotal" : null,
         "turnovers" : "0",
         "percent3Pt" : "0.00%",
         "pointsTotal" : null,
         "attempted2Pt" : "0",
         "made3Pt" : "0",
         "blocks" : "0",
         "percent2Pt" : "0.00%",
         "steals" : "0",
         "attemptedFt" : "0",
         "opponent" : "Pasco Bulldogs",
         "gameNumber" : 26,
         "made2Pt" : "0",
         "fouls" : "0",
         "defRebounds" : "0",
         "madeFt" : "0",
         "name" : "Mitchell",
         "assists" : "0",
         "attempted3Pt" : "0"
      },
      {
         "percentFt" : "0.00%",
         "turnovers" : "0",
         "percent3Pt" : "0.00%",
         "reboundsTotal" : null,
         "offRebounds" : "0",
         "gameType" : "Regionals",
         "percentTotal" : "0.00%",
         "opponent" : "Lewis and Clark Tigers",
         "steals" : "0",
         "percent2Pt" : "0.00%",
         "attemptedFt" : "0",
         "made3Pt" : "0",
         "attempted2Pt" : "0",
         "blocks" : "0",
         "pointsTotal" : null,
         "madeFt" : "0",
         "fouls" : "0",
         "defRebounds" : "0",
         "gameNumber" : 27,
         "made2Pt" : "0",
         "attempted3Pt" : "0",
         "name" : "Mitchell",
         "assists" : "0"
      },
      {
         "attempted3Pt" : "0",
         "assists" : "0",
         "name" : "Mitchell",
         "madeFt" : "0",
         "made2Pt" : "0",
         "gameNumber" : 28,
         "defRebounds" : 1,
         "fouls" : "0",
         "attemptedFt" : "0",
         "steals" : "0",
         "percent2Pt" : "0.00%",
         "opponent" : "Kentwood Conquerors",
         "pointsTotal" : null,
         "blocks" : "0",
         "made3Pt" : "0",
         "attempted2Pt" : "0",
         "turnovers" : "0",
         "percent3Pt" : "0.00%",
         "offRebounds" : "0",
         "reboundsTotal" : null,
         "percentFt" : "0.00%",
         "percentTotal" : "0.00%",
         "gameType" : "State"
      },
      {
         "opponent" : "Evergreen Plainsmen",
         "attemptedFt" : "0",
         "steals" : "0",
         "percent2Pt" : "0.00%",
         "blocks" : "0",
         "made3Pt" : "0",
         "attempted2Pt" : "0",
         "pointsTotal" : null,
         "percent3Pt" : "0.00%",
         "turnovers" : "0",
         "reboundsTotal" : null,
         "offRebounds" : "0",
         "percentFt" : "0.00%",
         "gameType" : "State",
         "percentTotal" : "0.00%",
         "attempted3Pt" : "0",
         "assists" : "0",
         "name" : "Mitchell",
         "madeFt" : "0",
         "defRebounds" : "0",
         "fouls" : "0",
         "made2Pt" : "0",
         "gameNumber" : 29
      },
      {
         "attempted3Pt" : "0",
         "name" : "Mitchell",
         "assists" : "0",
         "madeFt" : "0",
         "fouls" : "0",
         "defRebounds" : "0",
         "gameNumber" : 30,
         "made2Pt" : "0",
         "opponent" : "Kamiakin Braves",
         "percent2Pt" : "0.00%",
         "steals" : "0",
         "attemptedFt" : "0",
         "attempted2Pt" : "0",
         "made3Pt" : "0",
         "blocks" : "0",
         "pointsTotal" : null,
         "percentFt" : "0.00%",
         "reboundsTotal" : null,
         "offRebounds" : "0",
         "percent3Pt" : "0.00%",
         "turnovers" : "0",
         "gameType" : "State",
         "percentTotal" : "0.00%"
      }
   ],
   "name" : "Mitchell"
}
