{
   "date" : "1994-12-17",
   "winLoss" : "W",
   "opponent" : "Kennewick Lions",
   "teamTotals" : {
      "madeFt" : 10,
      "attemptedFt" : 17,
      "steals" : 7,
      "offRebounds" : 8,
      "blocks" : 7,
      "percentTotal" : "47.50%",
      "gameType" : "Conference",
      "fouls" : 17,
      "percent3Pt" : "44.00%",
      "name" : "Totals",
      "gameNumber" : 5,
      "attempted3Pt" : 25,
      "assists" : 12,
      "made2Pt" : 8,
      "percent2Pt" : "53.33%",
      "pointsTotal" : 59,
      "percentFt" : "58.82%",
      "attempted2Pt" : 15,
      "defRebounds" : 18,
      "made3Pt" : 11,
      "reboundsTotal" : 26,
      "opponent" : "Kennewick Lions",
      "turnovers" : 10
   },
   "opponentScore" : "36",
   "players" : [
      {
         "turnovers" : 1,
         "opponent" : "Kennewick Lions",
         "made3Pt" : 1,
         "reboundsTotal" : 2,
         "attempted2Pt" : 1,
         "percentFt" : "75.00%",
         "defRebounds" : 2,
         "percent2Pt" : "0.00%",
         "pointsTotal" : 6,
         "made2Pt" : "0",
         "attempted3Pt" : 3,
         "assists" : 3,
         "name" : "Spohr",
         "percent3Pt" : "33.33%",
         "fouls" : 2,
         "gameNumber" : 5,
         "gameType" : "Conference",
         "blocks" : "0",
         "percentTotal" : "25.00%",
         "offRebounds" : "0",
         "steals" : 3,
         "attemptedFt" : 4,
         "madeFt" : 3
      },
      {
         "turnovers" : 2,
         "made3Pt" : "0",
         "reboundsTotal" : 2,
         "opponent" : "Kennewick Lions",
         "percentFt" : "0.00%",
         "defRebounds" : 2,
         "attempted2Pt" : 1,
         "pointsTotal" : "0",
         "percent2Pt" : "0.00%",
         "made2Pt" : "0",
         "assists" : "0",
         "attempted3Pt" : 5,
         "gameNumber" : 5,
         "fouls" : "0",
         "percent3Pt" : "0.00%",
         "name" : "Buck",
         "percentTotal" : "0.00%",
         "blocks" : "0",
         "gameType" : "Conference",
         "offRebounds" : "0",
         "steals" : "0",
         "madeFt" : "0",
         "attemptedFt" : "0"
      },
      {
         "madeFt" : 1,
         "attemptedFt" : 2,
         "steals" : "0",
         "offRebounds" : "0",
         "blocks" : "0",
         "percentTotal" : "0.00%",
         "gameType" : "Conference",
         "gameNumber" : 5,
         "fouls" : 1,
         "percent3Pt" : "0.00%",
         "name" : "Siefken",
         "assists" : "0",
         "attempted3Pt" : "0",
         "made2Pt" : "0",
         "percent2Pt" : "0.00%",
         "pointsTotal" : 1,
         "attempted2Pt" : "0",
         "defRebounds" : 1,
         "percentFt" : "50.00%",
         "reboundsTotal" : 1,
         "made3Pt" : "0",
         "opponent" : "Kennewick Lions",
         "turnovers" : 1
      },
      {
         "pointsTotal" : 2,
         "percent2Pt" : "100.00%",
         "made2Pt" : 1,
         "turnovers" : "0",
         "reboundsTotal" : 2,
         "made3Pt" : "0",
         "opponent" : "Kennewick Lions",
         "attempted2Pt" : 1,
         "defRebounds" : 1,
         "percentFt" : "0.00%",
         "percentTotal" : "100.00%",
         "blocks" : "0",
         "gameType" : "Conference",
         "offRebounds" : 1,
         "steals" : "0",
         "madeFt" : "0",
         "attemptedFt" : "0",
         "attempted3Pt" : "0",
         "assists" : "0",
         "percent3Pt" : "0.00%",
         "fouls" : 4,
         "name" : "Bone",
         "gameNumber" : 5
      },
      {
         "offRebounds" : "0",
         "blocks" : "0",
         "percentTotal" : "0.00%",
         "gameType" : "Conference",
         "madeFt" : "0",
         "attemptedFt" : "0",
         "steals" : "0",
         "attempted3Pt" : "0",
         "assists" : "0",
         "percent3Pt" : "0.00%",
         "fouls" : "0",
         "name" : "Reed",
         "gameNumber" : 5,
         "made2Pt" : "0",
         "pointsTotal" : "0",
         "percent2Pt" : "0.00%",
         "turnovers" : "0",
         "defRebounds" : "0",
         "percentFt" : "0.00%",
         "attempted2Pt" : "0",
         "made3Pt" : "0",
         "reboundsTotal" : "0",
         "opponent" : "Kennewick Lions"
      },
      {
         "attempted2Pt" : 1,
         "percentFt" : "0.00%",
         "defRebounds" : "0",
         "opponent" : "Kennewick Lions",
         "reboundsTotal" : "0",
         "made3Pt" : 4,
         "turnovers" : "0",
         "made2Pt" : 1,
         "pointsTotal" : 14,
         "percent2Pt" : "100.00%",
         "name" : "Robertson",
         "fouls" : 1,
         "percent3Pt" : "40.00%",
         "gameNumber" : 5,
         "attempted3Pt" : 10,
         "assists" : 3,
         "attemptedFt" : "0",
         "madeFt" : "0",
         "steals" : 3,
         "offRebounds" : "0",
         "gameType" : "Conference",
         "blocks" : "0",
         "percentTotal" : "45.45%"
      },
      {
         "percent2Pt" : "80.00%",
         "pointsTotal" : 10,
         "made2Pt" : 4,
         "opponent" : "Kennewick Lions",
         "made3Pt" : "0",
         "reboundsTotal" : 4,
         "percentFt" : "66.67%",
         "attempted2Pt" : 5,
         "defRebounds" : 3,
         "turnovers" : 3,
         "steals" : "0",
         "attemptedFt" : 3,
         "madeFt" : 2,
         "gameType" : "Conference",
         "blocks" : 5,
         "percentTotal" : "80.00%",
         "offRebounds" : 1,
         "name" : "Schulz",
         "percent3Pt" : "0.00%",
         "fouls" : 4,
         "gameNumber" : 5,
         "attempted3Pt" : "0",
         "assists" : 2
      },
      {
         "assists" : 4,
         "attempted3Pt" : 7,
         "gameNumber" : 5,
         "name" : "Ash",
         "percent3Pt" : "85.71%",
         "fouls" : 1,
         "offRebounds" : 2,
         "gameType" : "Conference",
         "blocks" : "0",
         "percentTotal" : "70.00%",
         "attemptedFt" : 4,
         "madeFt" : 3,
         "steals" : "0",
         "turnovers" : 1,
         "defRebounds" : 6,
         "attempted2Pt" : 3,
         "percentFt" : "75.00%",
         "opponent" : "Kennewick Lions",
         "made3Pt" : 6,
         "reboundsTotal" : 8,
         "made2Pt" : 1,
         "pointsTotal" : 23,
         "percent2Pt" : "33.33%"
      },
      {
         "name" : "Cahill",
         "percent3Pt" : "0.00%",
         "fouls" : 4,
         "gameNumber" : 5,
         "attempted3Pt" : "0",
         "assists" : "0",
         "attemptedFt" : 4,
         "madeFt" : 1,
         "steals" : 1,
         "offRebounds" : 3,
         "gameType" : "Conference",
         "blocks" : "0",
         "percentTotal" : "50.00%",
         "attempted2Pt" : 2,
         "defRebounds" : 1,
         "percentFt" : "25.00%",
         "opponent" : "Kennewick Lions",
         "made3Pt" : "0",
         "reboundsTotal" : 4,
         "turnovers" : 2,
         "made2Pt" : 1,
         "pointsTotal" : 3,
         "percent2Pt" : "50.00%"
      },
      {
         "assists" : "0",
         "attempted3Pt" : "0",
         "gameNumber" : 5,
         "percent3Pt" : "0.00%",
         "fouls" : "0",
         "name" : "Coleman",
         "offRebounds" : 1,
         "percentTotal" : "0.00%",
         "blocks" : 2,
         "gameType" : "Conference",
         "madeFt" : "0",
         "attemptedFt" : "0",
         "steals" : "0",
         "turnovers" : "0",
         "defRebounds" : 2,
         "attempted2Pt" : 1,
         "percentFt" : "0.00%",
         "reboundsTotal" : 3,
         "made3Pt" : "0",
         "opponent" : "Kennewick Lions",
         "made2Pt" : "0",
         "percent2Pt" : "0.00%",
         "pointsTotal" : "0"
      },
      {
         "turnovers" : "0",
         "defRebounds" : "0",
         "attempted2Pt" : "0",
         "percentFt" : "0.00%",
         "made3Pt" : "0",
         "reboundsTotal" : "0",
         "opponent" : "Kennewick Lions",
         "made2Pt" : "0",
         "percent2Pt" : "0.00%",
         "pointsTotal" : "0",
         "attempted3Pt" : "0",
         "assists" : "0",
         "percent3Pt" : "0.00%",
         "fouls" : "0",
         "name" : "Merkley",
         "gameNumber" : 5,
         "offRebounds" : "0",
         "percentTotal" : "0.00%",
         "blocks" : "0",
         "gameType" : "Conference",
         "madeFt" : "0",
         "attemptedFt" : "0",
         "steals" : "0"
      }
   ],
   "gameFlowUrl" : "games/flows/gameflow05.json",
   "location" : "Away"
}

